map_dictionary_keys/__init__.py
map_dictionary_keys/map_dictionary_keys.py
tests/__init__.py
tests/test_data.py
tests/test_map_dictionary_keys.py
map_dictionary_keys-0.0.2.dist-info/LICENSE
map_dictionary_keys-0.0.2.dist-info/METADATA
map_dictionary_keys-0.0.2.dist-info/WHEEL
map_dictionary_keys-0.0.2.dist-info/top_level.txt
map_dictionary_keys-0.0.2.dist-info/RECORD
